[{"line":1,"elements":[{"start_timestamp":"2024-10-31T18:18:08.546Z","before":[{"result":{"duration":3959148200,"status":"passed"},"match":{"location":"com.juaracoding.soalautomation.impl.LoginOutlineHooks.setUp()"}}],"line":15,"name":"Test001 Signup Website (user)","description":"","id":"signup-website;test001-signup-website-(user);;2","after":[{"result":{"duration":329928800,"status":"passed"},"match":{"location":"com.juaracoding.soalautomation.impl.LoginOutlineHooks.closeObject()"}}],"type":"scenario","keyword":"Scenario","steps":[{"result":{"duration":4695751500,"status":"passed"},"line":3,"name":"Test001 Membuka Halaman Website","match":{"location":"com.juaracoding.soalautomation.impl.SignUpTesting.test001_membuka_halaman_login()"},"after":[{"result":{"duration":2540100,"status":"passed"},"match":{"location":"com.juaracoding.soalautomation.impl.LoginOutlineHooks.getResultStatus(io.cucumber.java.Scenario)"}}],"keyword":"When "},{"result":{"duration":3170071400,"status":"passed"},"line":4,"name":"Test001 Click Button SignUp","match":{"location":"com.juaracoding.soalautomation.impl.SignUpTesting.test001_click_signup()"},"after":[{"result":{"status":"passed"},"match":{"location":"com.juaracoding.soalautomation.impl.LoginOutlineHooks.getResultStatus(io.cucumber.java.Scenario)"}}],"keyword":"And "},{"result":{"duration":3044605700,"status":"passed"},"line":5,"name":"Test001 Validasi SignUp","match":{"location":"com.juaracoding.soalautomation.impl.SignUpTesting.test001_validasi_signup()"},"after":[{"result":{"status":"passed"},"match":{"location":"com.juaracoding.soalautomation.impl.LoginOutlineHooks.getResultStatus(io.cucumber.java.Scenario)"}}],"keyword":"And "},{"result":{"duration":3162350700,"status":"passed"},"line":6,"name":"Test001 Input TextField jajajakcvasdg777779 Yang Valid One","match":{"arguments":[{"val":"jajajakcvasdg777779","offset":24}],"location":"com.juaracoding.soalautomation.impl.SignUpTesting.test001_input_textfield_username_yang_valid_one(java.lang.String)"},"after":[{"result":{"status":"passed"},"match":{"location":"com.juaracoding.soalautomation.impl.LoginOutlineHooks.getResultStatus(io.cucumber.java.Scenario)"}}],"keyword":"And "},{"result":{"duration":6150245900,"status":"passed"},"line":7,"name":"Test001 Input TextField jajak4k4 Yang Valid Two","match":{"arguments":[{"val":"jajak4k4","offset":24}],"location":"com.juaracoding.soalautomation.impl.SignUpTesting.test001_input_textfield_password_yang_valid_one(java.lang.String)"},"after":[{"result":{"duration":194400,"status":"passed"},"match":{"location":"com.juaracoding.soalautomation.impl.LoginOutlineHooks.getResultStatus(io.cucumber.java.Scenario)"}}],"keyword":"And "},{"result":{"duration":3030081500,"status":"passed"},"line":8,"name":"Test001 Validasi Form Sign UP","match":{"location":"com.juaracoding.soalautomation.impl.SignUpTesting.test001_validasi_form_sign_up()"},"after":[{"result":{"status":"passed"},"match":{"location":"com.juaracoding.soalautomation.impl.LoginOutlineHooks.getResultStatus(io.cucumber.java.Scenario)"}}],"keyword":"And "},{"result":{"duration":3108910500,"status":"passed"},"line":9,"name":"Test001 Click Button SignUp Form","match":{"location":"com.juaracoding.soalautomation.impl.SignUpTesting.test001_click_button_signup()"},"after":[{"result":{"status":"passed"},"match":{"location":"com.juaracoding.soalautomation.impl.LoginOutlineHooks.getResultStatus(io.cucumber.java.Scenario)"}}],"keyword":"And "},{"result":{"duration":6033449300,"status":"passed"},"line":10,"name":"Test001 Pop Out Sign Up Berhasil","match":{"location":"com.juaracoding.soalautomation.impl.SignUpTesting.test001_pop_out_sign_up_berhasil()"},"after":[{"result":{"duration":20900,"status":"passed"},"match":{"location":"com.juaracoding.soalautomation.impl.LoginOutlineHooks.getResultStatus(io.cucumber.java.Scenario)"}}],"keyword":"Then "}]}],"name":"SignUp Website","description":"","id":"signup-website","keyword":"Feature","uri":"file:src/main/resources/features/001SignUpFeature.feature","tags":[]},{"line":1,"elements":[{"start_timestamp":"2024-10-31T18:18:45.272Z","before":[{"result":{"status":"passed"},"match":{"location":"com.juaracoding.soalautomation.impl.LoginOutlineHooks.setUp()"}}],"line":12,"name":"Test002 LogIn Website (user)","description":"","id":"login-website;test002-login-website-(user);;2","after":[{"result":{"duration":40898100,"status":"passed"},"match":{"location":"com.juaracoding.soalautomation.impl.LoginOutlineHooks.closeObject()"}}],"type":"scenario","keyword":"Scenario","steps":[{"result":{"duration":3134028300,"status":"passed"},"line":3,"name":"Test002 Click Button Log In","match":{"location":"com.juaracoding.soalautomation.impl.LoginTesting.test002_click_button_log_in()"},"after":[{"result":{"status":"passed"},"match":{"location":"com.juaracoding.soalautomation.impl.LoginOutlineHooks.getResultStatus(io.cucumber.java.Scenario)"}}],"keyword":"When "},{"result":{"duration":3035489100,"status":"passed"},"line":4,"name":"Test002 Validasi Log In","match":{"location":"com.juaracoding.soalautomation.impl.LoginTesting.test002_validasi_log_in()"},"after":[{"result":{"status":"passed"},"match":{"location":"com.juaracoding.soalautomation.impl.LoginOutlineHooks.getResultStatus(io.cucumber.java.Scenario)"}}],"keyword":"And "},{"result":{"duration":3128988200,"status":"passed"},"line":5,"name":"Test002 Input TextField jajajakcvasdg777779 Yang Valid One","match":{"arguments":[{"val":"jajajakcvasdg777779","offset":24}],"location":"com.juaracoding.soalautomation.impl.LoginTesting.test002_input_textfield_username_yang_valid_one(java.lang.String)"},"after":[{"result":{"status":"passed"},"match":{"location":"com.juaracoding.soalautomation.impl.LoginOutlineHooks.getResultStatus(io.cucumber.java.Scenario)"}}],"keyword":"And "},{"result":{"duration":3109325100,"status":"passed"},"line":6,"name":"Test002 Input TextField jajak4k4 Yang Valid Two","match":{"arguments":[{"val":"jajak4k4","offset":24}],"location":"com.juaracoding.soalautomation.impl.LoginTesting.test002_input_textfield_password_yang_valid_one(java.lang.String)"},"after":[{"result":{"status":"passed"},"match":{"location":"com.juaracoding.soalautomation.impl.LoginOutlineHooks.getResultStatus(io.cucumber.java.Scenario)"}}],"keyword":"And "},{"result":{"duration":99906000,"status":"passed"},"line":7,"name":"Test002 Click Button Login Form","match":{"location":"com.juaracoding.soalautomation.impl.LoginTesting.test002_click_button_log_in_form()"},"after":[{"result":{"duration":291400,"status":"passed"},"match":{"location":"com.juaracoding.soalautomation.impl.LoginOutlineHooks.getResultStatus(io.cucumber.java.Scenario)"}}],"keyword":"Then "}]}],"name":"LogIn Website","description":"","id":"login-website","keyword":"Feature","uri":"file:src/main/resources/features/002LoginFeature.feature","tags":[]},{"line":1,"elements":[{"start_timestamp":"2024-10-31T18:18:57.845Z","before":[{"result":{"duration":1033300,"status":"passed"},"match":{"location":"com.juaracoding.soalautomation.impl.LoginOutlineHooks.setUp()"}}],"line":2,"name":"Test003 Cart Samsung Galaxy S6","description":"","id":"cart-website;test003-cart-samsung-galaxy-s6","after":[{"result":{"duration":141376200,"status":"passed"},"match":{"location":"com.juaracoding.soalautomation.impl.LoginOutlineHooks.closeObject()"}}],"type":"scenario","keyword":"Scenario","steps":[{"result":{"error_message":"org.openqa.selenium.UnhandledAlertException: unexpected alert open: {Alert text : User does not exist.}\n  (Session info: chrome=130.0.6723.92): User does not exist.\nBuild info: version: '4.19.1', revision: 'abe0ee07dc'\nSystem info: os.name: 'Windows 10', os.arch: 'amd64', os.version: '10.0', java.version: '17.0.8'\nDriver info: org.openqa.selenium.chrome.ChromeDriver\nCommand: [6620f8f3aa088ee1244b99544fcb7077, findElement {value=//a[@id='nava'], using=xpath}]\nCapabilities {acceptInsecureCerts: false, browserName: chrome, browserVersion: 130.0.6723.92, chrome: {chromedriverVersion: 130.0.6723.91 (53ac07678369..., userDataDir: C:\\Users\\MSI\\AppData\\Local\\...}, fedcm:accounts: true, goog:chromeOptions: {debuggerAddress: localhost:64392}, networkConnectionEnabled: false, pageLoadStrategy: normal, platformName: windows, proxy: Proxy(), se:cdp: ws://localhost:64392/devtoo..., se:cdpVersion: 130.0.6723.92, setWindowRect: true, strictFileInteractability: false, timeouts: {implicit: 0, pageLoad: 300000, script: 30000}, unhandledPromptBehavior: dismiss and notify, webauthn:extension:credBlob: true, webauthn:extension:largeBlob: true, webauthn:extension:minPinLength: true, webauthn:extension:prf: true, webauthn:virtualAuthenticators: true}\nSession ID: 6620f8f3aa088ee1244b99544fcb7077\r\n\tat org.openqa.selenium.remote.codec.w3c.W3CHttpResponseCodec.decode(W3CHttpResponseCodec.java:136)\r\n\tat org.openqa.selenium.remote.codec.w3c.W3CHttpResponseCodec.decode(W3CHttpResponseCodec.java:50)\r\n\tat org.openqa.selenium.remote.HttpCommandExecutor.execute(HttpCommandExecutor.java:190)\r\n\tat org.openqa.selenium.remote.service.DriverCommandExecutor.invokeExecute(DriverCommandExecutor.java:216)\r\n\tat org.openqa.selenium.remote.service.DriverCommandExecutor.execute(DriverCommandExecutor.java:174)\r\n\tat org.openqa.selenium.remote.RemoteWebDriver.execute(RemoteWebDriver.java:518)\r\n\tat org.openqa.selenium.remote.ElementLocation$ElementFinder$2.findElement(ElementLocation.java:165)\r\n\tat org.openqa.selenium.remote.ElementLocation.findElement(ElementLocation.java:59)\r\n\tat org.openqa.selenium.remote.RemoteWebDriver.findElement(RemoteWebDriver.java:355)\r\n\tat org.openqa.selenium.remote.RemoteWebDriver.findElement(RemoteWebDriver.java:349)\r\n\tat org.openqa.selenium.support.pagefactory.DefaultElementLocator.findElement(DefaultElementLocator.java:68)\r\n\tat org.openqa.selenium.support.pagefactory.internal.LocatingElementHandler.invoke(LocatingElementHandler.java:38)\r\n\tat jdk.proxy2/jdk.proxy2.$Proxy27.getText(Unknown Source)\r\n\tat com.juaracoding.soalautomation.page.HomePage.homePageValidation(HomePage.java:61)\r\n\tat com.juaracoding.soalautomation.impl.CartTesting.test003_validasi_website(CartTesting.java:52)\r\n\tat ✽.Test003 Validasi website(file:///D:/Bootcamp%20SQA%20Juara%20Koding/SoalTestAutomation/src/main/resources/features/003CartFeature.feature:3)\r\n","duration":3235086800,"status":"failed"},"line":3,"name":"Test003 Validasi website","match":{"location":"com.juaracoding.soalautomation.impl.CartTesting.test003_validasi_website()"},"after":[{"result":{"duration":329165400,"status":"passed"},"match":{"location":"com.juaracoding.soalautomation.impl.LoginOutlineHooks.getResultStatus(io.cucumber.java.Scenario)"}}],"keyword":"When "},{"result":{"status":"skipped"},"line":4,"name":"Test003 Membuka Item Samsung Galaxy S6","match":{"location":"com.juaracoding.soalautomation.impl.CartTesting.test003_membuka_item_samsung_galaxy_s6()"},"after":[{"result":{"duration":149100,"status":"skipped"},"match":{"location":"com.juaracoding.soalautomation.impl.LoginOutlineHooks.getResultStatus(io.cucumber.java.Scenario)"}}],"keyword":"And "},{"result":{"status":"skipped"},"line":5,"name":"Test003 Click Button Add To Cart","match":{"location":"com.juaracoding.soalautomation.impl.CartTesting.test003_click_button_add_to_cart()"},"after":[{"result":{"status":"skipped"},"match":{"location":"com.juaracoding.soalautomation.impl.LoginOutlineHooks.getResultStatus(io.cucumber.java.Scenario)"}}],"keyword":"And "},{"result":{"status":"skipped"},"line":6,"name":"Test003 Klik Ok Pop Up","match":{"location":"com.juaracoding.soalautomation.impl.CartTesting.test003_klik_ok_pop_up()"},"after":[{"result":{"status":"skipped"},"match":{"location":"com.juaracoding.soalautomation.impl.LoginOutlineHooks.getResultStatus(io.cucumber.java.Scenario)"}}],"keyword":"Then "}]},{"start_timestamp":"2024-10-31T18:19:01.586Z","before":[{"result":{"status":"passed"},"match":{"location":"com.juaracoding.soalautomation.impl.LoginOutlineHooks.setUp()"}}],"line":8,"name":"Test004 Cart Nokia Lumia 1520","description":"","id":"cart-website;test004-cart-nokia-lumia-1520","after":[{"result":{"duration":48170200,"status":"passed"},"match":{"location":"com.juaracoding.soalautomation.impl.LoginOutlineHooks.closeObject()"}}],"type":"scenario","keyword":"Scenario","steps":[{"result":{"error_message":"org.openqa.selenium.ElementClickInterceptedException: element click intercepted: Element <a class=\"nav-link\" href=\"index.html\">...</a> is not clickable at point (865, 37). Other element would receive the click: <div class=\"modal-header\">...</div>\n  (Session info: chrome=130.0.6723.92)\nBuild info: version: '4.19.1', revision: 'abe0ee07dc'\nSystem info: os.name: 'Windows 10', os.arch: 'amd64', os.version: '10.0', java.version: '17.0.8'\nDriver info: org.openqa.selenium.chrome.ChromeDriver\nCommand: [6620f8f3aa088ee1244b99544fcb7077, clickElement {id=f.79DC775009CF74B632EB6740EE009FE3.d.CC98061A3499600B33493E181DC143A8.e.107}]\nCapabilities {acceptInsecureCerts: false, browserName: chrome, browserVersion: 130.0.6723.92, chrome: {chromedriverVersion: 130.0.6723.91 (53ac07678369..., userDataDir: C:\\Users\\MSI\\AppData\\Local\\...}, fedcm:accounts: true, goog:chromeOptions: {debuggerAddress: localhost:64392}, networkConnectionEnabled: false, pageLoadStrategy: normal, platformName: windows, proxy: Proxy(), se:cdp: ws://localhost:64392/devtoo..., se:cdpVersion: 130.0.6723.92, setWindowRect: true, strictFileInteractability: false, timeouts: {implicit: 0, pageLoad: 300000, script: 30000}, unhandledPromptBehavior: dismiss and notify, webauthn:extension:credBlob: true, webauthn:extension:largeBlob: true, webauthn:extension:minPinLength: true, webauthn:extension:prf: true, webauthn:virtualAuthenticators: true}\nElement: [[ChromeDriver: chrome on windows (6620f8f3aa088ee1244b99544fcb7077)] -> xpath: //li[@class='nav-item active']//a[@class='nav-link']]\nSession ID: 6620f8f3aa088ee1244b99544fcb7077\r\n\tat java.base/jdk.internal.reflect.NativeConstructorAccessorImpl.newInstance0(Native Method)\r\n\tat java.base/jdk.internal.reflect.NativeConstructorAccessorImpl.newInstance(NativeConstructorAccessorImpl.java:77)\r\n\tat java.base/jdk.internal.reflect.DelegatingConstructorAccessorImpl.newInstance(DelegatingConstructorAccessorImpl.java:45)\r\n\tat java.base/java.lang.reflect.Constructor.newInstanceWithCaller(Constructor.java:499)\r\n\tat java.base/java.lang.reflect.Constructor.newInstance(Constructor.java:480)\r\n\tat org.openqa.selenium.remote.ErrorCodec.decode(ErrorCodec.java:167)\r\n\tat org.openqa.selenium.remote.codec.w3c.W3CHttpResponseCodec.decode(W3CHttpResponseCodec.java:138)\r\n\tat org.openqa.selenium.remote.codec.w3c.W3CHttpResponseCodec.decode(W3CHttpResponseCodec.java:50)\r\n\tat org.openqa.selenium.remote.HttpCommandExecutor.execute(HttpCommandExecutor.java:190)\r\n\tat org.openqa.selenium.remote.service.DriverCommandExecutor.invokeExecute(DriverCommandExecutor.java:216)\r\n\tat org.openqa.selenium.remote.service.DriverCommandExecutor.execute(DriverCommandExecutor.java:174)\r\n\tat org.openqa.selenium.remote.RemoteWebDriver.execute(RemoteWebDriver.java:518)\r\n\tat org.openqa.selenium.remote.RemoteWebElement.execute(RemoteWebElement.java:223)\r\n\tat org.openqa.selenium.remote.RemoteWebElement.click(RemoteWebElement.java:76)\r\n\tat java.base/jdk.internal.reflect.NativeMethodAccessorImpl.invoke0(Native Method)\r\n\tat java.base/jdk.internal.reflect.NativeMethodAccessorImpl.invoke(NativeMethodAccessorImpl.java:77)\r\n\tat java.base/jdk.internal.reflect.DelegatingMethodAccessorImpl.invoke(DelegatingMethodAccessorImpl.java:43)\r\n\tat java.base/java.lang.reflect.Method.invoke(Method.java:568)\r\n\tat org.openqa.selenium.support.pagefactory.internal.LocatingElementHandler.invoke(LocatingElementHandler.java:51)\r\n\tat jdk.proxy2/jdk.proxy2.$Proxy27.click(Unknown Source)\r\n\tat com.juaracoding.soalautomation.page.ItemPage.SetBtnHome(ItemPage.java:56)\r\n\tat com.juaracoding.soalautomation.impl.CartTesting.test003_click_button_home(CartTesting.java:76)\r\n\tat ✽.Test004 Click Button Home(file:///D:/Bootcamp%20SQA%20Juara%20Koding/SoalTestAutomation/src/main/resources/features/003CartFeature.feature:9)\r\n","duration":4101090400,"status":"failed"},"line":9,"name":"Test004 Click Button Home","match":{"location":"com.juaracoding.soalautomation.impl.CartTesting.test003_click_button_home()"},"after":[{"result":{"duration":203757100,"status":"passed"},"match":{"location":"com.juaracoding.soalautomation.impl.LoginOutlineHooks.getResultStatus(io.cucumber.java.Scenario)"}}],"keyword":"When "},{"result":{"status":"skipped"},"line":10,"name":"Test004 Validasi website","match":{"location":"com.juaracoding.soalautomation.impl.CartTesting.test004_validasi_website()"},"after":[{"result":{"status":"skipped"},"match":{"location":"com.juaracoding.soalautomation.impl.LoginOutlineHooks.getResultStatus(io.cucumber.java.Scenario)"}}],"keyword":"And "},{"result":{"status":"skipped"},"line":11,"name":"Test004 Membuka Item Nokia Lumia 1520","match":{"location":"com.juaracoding.soalautomation.impl.CartTesting.test004_membuka_item_nokia_lumia_1520()"},"after":[{"result":{"status":"skipped"},"match":{"location":"com.juaracoding.soalautomation.impl.LoginOutlineHooks.getResultStatus(io.cucumber.java.Scenario)"}}],"keyword":"And "},{"result":{"status":"skipped"},"line":12,"name":"Test004 Click Button Add To Cart","match":{"location":"com.juaracoding.soalautomation.impl.CartTesting.test004_click_button_add_to_cart()"},"after":[{"result":{"status":"skipped"},"match":{"location":"com.juaracoding.soalautomation.impl.LoginOutlineHooks.getResultStatus(io.cucumber.java.Scenario)"}}],"keyword":"And "},{"result":{"status":"skipped"},"line":13,"name":"Test004 Klik Ok Pop Up","match":{"location":"com.juaracoding.soalautomation.impl.CartTesting.test004_klik_ok_pop_up()"},"after":[{"result":{"status":"skipped"},"match":{"location":"com.juaracoding.soalautomation.impl.LoginOutlineHooks.getResultStatus(io.cucumber.java.Scenario)"}}],"keyword":"Then "}]},{"start_timestamp":"2024-10-31T18:19:05.968Z","before":[{"result":{"duration":339600,"status":"passed"},"match":{"location":"com.juaracoding.soalautomation.impl.LoginOutlineHooks.setUp()"}}],"line":15,"name":"Test005 Cart Nexus6","description":"","id":"cart-website;test005-cart-nexus6","after":[{"result":{"duration":38676400,"status":"passed"},"match":{"location":"com.juaracoding.soalautomation.impl.LoginOutlineHooks.closeObject()"}}],"type":"scenario","keyword":"Scenario","steps":[{"result":{"error_message":"org.openqa.selenium.ElementClickInterceptedException: element click intercepted: Element <a class=\"nav-link\" href=\"index.html\">...</a> is not clickable at point (865, 37). Other element would receive the click: <div class=\"modal-header\">...</div>\n  (Session info: chrome=130.0.6723.92)\nBuild info: version: '4.19.1', revision: 'abe0ee07dc'\nSystem info: os.name: 'Windows 10', os.arch: 'amd64', os.version: '10.0', java.version: '17.0.8'\nDriver info: org.openqa.selenium.chrome.ChromeDriver\nCommand: [6620f8f3aa088ee1244b99544fcb7077, clickElement {id=f.79DC775009CF74B632EB6740EE009FE3.d.CC98061A3499600B33493E181DC143A8.e.107}]\nCapabilities {acceptInsecureCerts: false, browserName: chrome, browserVersion: 130.0.6723.92, chrome: {chromedriverVersion: 130.0.6723.91 (53ac07678369..., userDataDir: C:\\Users\\MSI\\AppData\\Local\\...}, fedcm:accounts: true, goog:chromeOptions: {debuggerAddress: localhost:64392}, networkConnectionEnabled: false, pageLoadStrategy: normal, platformName: windows, proxy: Proxy(), se:cdp: ws://localhost:64392/devtoo..., se:cdpVersion: 130.0.6723.92, setWindowRect: true, strictFileInteractability: false, timeouts: {implicit: 0, pageLoad: 300000, script: 30000}, unhandledPromptBehavior: dismiss and notify, webauthn:extension:credBlob: true, webauthn:extension:largeBlob: true, webauthn:extension:minPinLength: true, webauthn:extension:prf: true, webauthn:virtualAuthenticators: true}\nElement: [[ChromeDriver: chrome on windows (6620f8f3aa088ee1244b99544fcb7077)] -> xpath: //li[@class='nav-item active']//a[@class='nav-link']]\nSession ID: 6620f8f3aa088ee1244b99544fcb7077\r\n\tat java.base/jdk.internal.reflect.NativeConstructorAccessorImpl.newInstance0(Native Method)\r\n\tat java.base/jdk.internal.reflect.NativeConstructorAccessorImpl.newInstance(NativeConstructorAccessorImpl.java:77)\r\n\tat java.base/jdk.internal.reflect.DelegatingConstructorAccessorImpl.newInstance(DelegatingConstructorAccessorImpl.java:45)\r\n\tat java.base/java.lang.reflect.Constructor.newInstanceWithCaller(Constructor.java:499)\r\n\tat java.base/java.lang.reflect.Constructor.newInstance(Constructor.java:480)\r\n\tat org.openqa.selenium.remote.ErrorCodec.decode(ErrorCodec.java:167)\r\n\tat org.openqa.selenium.remote.codec.w3c.W3CHttpResponseCodec.decode(W3CHttpResponseCodec.java:138)\r\n\tat org.openqa.selenium.remote.codec.w3c.W3CHttpResponseCodec.decode(W3CHttpResponseCodec.java:50)\r\n\tat org.openqa.selenium.remote.HttpCommandExecutor.execute(HttpCommandExecutor.java:190)\r\n\tat org.openqa.selenium.remote.service.DriverCommandExecutor.invokeExecute(DriverCommandExecutor.java:216)\r\n\tat org.openqa.selenium.remote.service.DriverCommandExecutor.execute(DriverCommandExecutor.java:174)\r\n\tat org.openqa.selenium.remote.RemoteWebDriver.execute(RemoteWebDriver.java:518)\r\n\tat org.openqa.selenium.remote.RemoteWebElement.execute(RemoteWebElement.java:223)\r\n\tat org.openqa.selenium.remote.RemoteWebElement.click(RemoteWebElement.java:76)\r\n\tat java.base/jdk.internal.reflect.NativeMethodAccessorImpl.invoke0(Native Method)\r\n\tat java.base/jdk.internal.reflect.NativeMethodAccessorImpl.invoke(NativeMethodAccessorImpl.java:77)\r\n\tat java.base/jdk.internal.reflect.DelegatingMethodAccessorImpl.invoke(DelegatingMethodAccessorImpl.java:43)\r\n\tat java.base/java.lang.reflect.Method.invoke(Method.java:568)\r\n\tat org.openqa.selenium.support.pagefactory.internal.LocatingElementHandler.invoke(LocatingElementHandler.java:51)\r\n\tat jdk.proxy2/jdk.proxy2.$Proxy27.click(Unknown Source)\r\n\tat com.juaracoding.soalautomation.page.ItemPage.SetBtnHome(ItemPage.java:56)\r\n\tat com.juaracoding.soalautomation.impl.CartTesting.test005_click_button_home(CartTesting.java:106)\r\n\tat ✽.Test005 Click Button Home(file:///D:/Bootcamp%20SQA%20Juara%20Koding/SoalTestAutomation/src/main/resources/features/003CartFeature.feature:16)\r\n","duration":4144752400,"status":"failed"},"line":16,"name":"Test005 Click Button Home","match":{"location":"com.juaracoding.soalautomation.impl.CartTesting.test005_click_button_home()"},"after":[{"result":{"duration":221364500,"status":"passed"},"match":{"location":"com.juaracoding.soalautomation.impl.LoginOutlineHooks.getResultStatus(io.cucumber.java.Scenario)"}}],"keyword":"When "},{"result":{"status":"skipped"},"line":17,"name":"Test005 Validasi website","match":{"location":"com.juaracoding.soalautomation.impl.CartTesting.test005_validasi_website()"},"after":[{"result":{"status":"skipped"},"match":{"location":"com.juaracoding.soalautomation.impl.LoginOutlineHooks.getResultStatus(io.cucumber.java.Scenario)"}}],"keyword":"And "},{"result":{"status":"skipped"},"line":18,"name":"Test005 Membuka Item Nexus6","match":{"location":"com.juaracoding.soalautomation.impl.CartTesting.test005_membuka_item_Nexus6()"},"after":[{"result":{"status":"skipped"},"match":{"location":"com.juaracoding.soalautomation.impl.LoginOutlineHooks.getResultStatus(io.cucumber.java.Scenario)"}}],"keyword":"And "},{"result":{"status":"skipped"},"line":19,"name":"Test005 Click Button Add To Cart","match":{"location":"com.juaracoding.soalautomation.impl.CartTesting.test005_click_button_add_to_cart()"},"after":[{"result":{"status":"skipped"},"match":{"location":"com.juaracoding.soalautomation.impl.LoginOutlineHooks.getResultStatus(io.cucumber.java.Scenario)"}}],"keyword":"And "},{"result":{"status":"skipped"},"line":20,"name":"Test005 Klik Ok Pop Up","match":{"location":"com.juaracoding.soalautomation.impl.CartTesting.test005_klik_ok_pop_up()"},"after":[{"result":{"status":"skipped"},"match":{"location":"com.juaracoding.soalautomation.impl.LoginOutlineHooks.getResultStatus(io.cucumber.java.Scenario)"}}],"keyword":"Then "}]},{"start_timestamp":"2024-10-31T18:19:10.398Z","before":[{"result":{"status":"passed"},"match":{"location":"com.juaracoding.soalautomation.impl.LoginOutlineHooks.setUp()"}}],"line":22,"name":"Test006 Cart Item","description":"","id":"cart-website;test006-cart-item","after":[{"result":{"duration":33875400,"status":"passed"},"match":{"location":"com.juaracoding.soalautomation.impl.LoginOutlineHooks.closeObject()"}}],"type":"scenario","keyword":"Scenario","steps":[{"result":{"error_message":"org.openqa.selenium.ElementClickInterceptedException: element click intercepted: Element <a class=\"nav-link\" id=\"cartur\" href=\"cart.html\">...</a> is not clickable at point (1068, 37). Other element would receive the click: <div class=\"modal fade show\" id=\"logInModal\" tabindex=\"-1\" role=\"dialog\" aria-labelledby=\"logInModalLabel\" style=\"display: block;\">...</div>\n  (Session info: chrome=130.0.6723.92)\nBuild info: version: '4.19.1', revision: 'abe0ee07dc'\nSystem info: os.name: 'Windows 10', os.arch: 'amd64', os.version: '10.0', java.version: '17.0.8'\nDriver info: org.openqa.selenium.chrome.ChromeDriver\nCommand: [6620f8f3aa088ee1244b99544fcb7077, clickElement {id=f.79DC775009CF74B632EB6740EE009FE3.d.CC98061A3499600B33493E181DC143A8.e.108}]\nCapabilities {acceptInsecureCerts: false, browserName: chrome, browserVersion: 130.0.6723.92, chrome: {chromedriverVersion: 130.0.6723.91 (53ac07678369..., userDataDir: C:\\Users\\MSI\\AppData\\Local\\...}, fedcm:accounts: true, goog:chromeOptions: {debuggerAddress: localhost:64392}, networkConnectionEnabled: false, pageLoadStrategy: normal, platformName: windows, proxy: Proxy(), se:cdp: ws://localhost:64392/devtoo..., se:cdpVersion: 130.0.6723.92, setWindowRect: true, strictFileInteractability: false, timeouts: {implicit: 0, pageLoad: 300000, script: 30000}, unhandledPromptBehavior: dismiss and notify, webauthn:extension:credBlob: true, webauthn:extension:largeBlob: true, webauthn:extension:minPinLength: true, webauthn:extension:prf: true, webauthn:virtualAuthenticators: true}\nElement: [[ChromeDriver: chrome on windows (6620f8f3aa088ee1244b99544fcb7077)] -> xpath: //a[@id='cartur']]\nSession ID: 6620f8f3aa088ee1244b99544fcb7077\r\n\tat java.base/jdk.internal.reflect.NativeConstructorAccessorImpl.newInstance0(Native Method)\r\n\tat java.base/jdk.internal.reflect.NativeConstructorAccessorImpl.newInstance(NativeConstructorAccessorImpl.java:77)\r\n\tat java.base/jdk.internal.reflect.DelegatingConstructorAccessorImpl.newInstance(DelegatingConstructorAccessorImpl.java:45)\r\n\tat java.base/java.lang.reflect.Constructor.newInstanceWithCaller(Constructor.java:499)\r\n\tat java.base/java.lang.reflect.Constructor.newInstance(Constructor.java:480)\r\n\tat org.openqa.selenium.remote.ErrorCodec.decode(ErrorCodec.java:167)\r\n\tat org.openqa.selenium.remote.codec.w3c.W3CHttpResponseCodec.decode(W3CHttpResponseCodec.java:138)\r\n\tat org.openqa.selenium.remote.codec.w3c.W3CHttpResponseCodec.decode(W3CHttpResponseCodec.java:50)\r\n\tat org.openqa.selenium.remote.HttpCommandExecutor.execute(HttpCommandExecutor.java:190)\r\n\tat org.openqa.selenium.remote.service.DriverCommandExecutor.invokeExecute(DriverCommandExecutor.java:216)\r\n\tat org.openqa.selenium.remote.service.DriverCommandExecutor.execute(DriverCommandExecutor.java:174)\r\n\tat org.openqa.selenium.remote.RemoteWebDriver.execute(RemoteWebDriver.java:518)\r\n\tat org.openqa.selenium.remote.RemoteWebElement.execute(RemoteWebElement.java:223)\r\n\tat org.openqa.selenium.remote.RemoteWebElement.click(RemoteWebElement.java:76)\r\n\tat java.base/jdk.internal.reflect.NativeMethodAccessorImpl.invoke0(Native Method)\r\n\tat java.base/jdk.internal.reflect.NativeMethodAccessorImpl.invoke(NativeMethodAccessorImpl.java:77)\r\n\tat java.base/jdk.internal.reflect.DelegatingMethodAccessorImpl.invoke(DelegatingMethodAccessorImpl.java:43)\r\n\tat java.base/java.lang.reflect.Method.invoke(Method.java:568)\r\n\tat org.openqa.selenium.support.pagefactory.internal.LocatingElementHandler.invoke(LocatingElementHandler.java:51)\r\n\tat jdk.proxy2/jdk.proxy2.$Proxy27.click(Unknown Source)\r\n\tat com.juaracoding.soalautomation.page.ItemPage.SetBtnCart(ItemPage.java:60)\r\n\tat com.juaracoding.soalautomation.impl.CartTesting.test006_click_button_cart(CartTesting.java:136)\r\n\tat ✽.Test006 Click Button Cart(file:///D:/Bootcamp%20SQA%20Juara%20Koding/SoalTestAutomation/src/main/resources/features/003CartFeature.feature:23)\r\n","duration":4152657400,"status":"failed"},"line":23,"name":"Test006 Click Button Cart","match":{"location":"com.juaracoding.soalautomation.impl.CartTesting.test006_click_button_cart()"},"after":[{"result":{"duration":219023700,"status":"passed"},"match":{"location":"com.juaracoding.soalautomation.impl.LoginOutlineHooks.getResultStatus(io.cucumber.java.Scenario)"}}],"keyword":"When "},{"result":{"status":"skipped"},"line":24,"name":"Test006 Validasi Cart Page","match":{"location":"com.juaracoding.soalautomation.impl.CartTesting.test006_validasi_cart_page()"},"after":[{"result":{"status":"skipped"},"match":{"location":"com.juaracoding.soalautomation.impl.LoginOutlineHooks.getResultStatus(io.cucumber.java.Scenario)"}}],"keyword":"And "},{"result":{"status":"skipped"},"line":25,"name":"Test006 Click Button Place Order","match":{"location":"com.juaracoding.soalautomation.impl.CartTesting.test006_click_button_place_order()"},"after":[{"result":{"duration":646000,"status":"skipped"},"match":{"location":"com.juaracoding.soalautomation.impl.LoginOutlineHooks.getResultStatus(io.cucumber.java.Scenario)"}}],"keyword":"Then "}]}],"name":"Cart Website","description":"","id":"cart-website","keyword":"Feature","uri":"file:src/main/resources/features/003CartFeature.feature","tags":[]},{"line":1,"elements":[{"start_timestamp":"2024-10-31T18:19:14.839Z","before":[{"result":{"duration":287000,"status":"passed"},"match":{"location":"com.juaracoding.soalautomation.impl.LoginOutlineHooks.setUp()"}}],"line":18,"name":"Test007 Checkout Item","description":"","id":"checkout-website;test007-checkout-item;;2","after":[{"result":{"duration":215997300,"status":"passed"},"match":{"location":"com.juaracoding.soalautomation.impl.LoginOutlineHooks.closeObject()"}}],"type":"scenario","keyword":"Scenario","steps":[{"result":{"error_message":"org.openqa.selenium.NoSuchElementException: Unable to find element with locator By.id: orderModalLabel\nFor documentation on this error, please visit: https://www.selenium.dev/documentation/webdriver/troubleshooting/errors#no-such-element-exception\nBuild info: version: '4.19.1', revision: 'abe0ee07dc'\nSystem info: os.name: 'Windows 10', os.arch: 'amd64', os.version: '10.0', java.version: '17.0.8'\nDriver info: driver.version: RemoteWebDriver\r\n\tat org.openqa.selenium.remote.ElementLocation$ElementFinder$2.findElement(ElementLocation.java:168)\r\n\tat org.openqa.selenium.remote.ElementLocation.findElement(ElementLocation.java:59)\r\n\tat org.openqa.selenium.remote.RemoteWebDriver.findElement(RemoteWebDriver.java:355)\r\n\tat org.openqa.selenium.remote.RemoteWebDriver.findElement(RemoteWebDriver.java:349)\r\n\tat org.openqa.selenium.support.pagefactory.DefaultElementLocator.findElement(DefaultElementLocator.java:68)\r\n\tat org.openqa.selenium.support.pagefactory.internal.LocatingElementHandler.invoke(LocatingElementHandler.java:38)\r\n\tat jdk.proxy2/jdk.proxy2.$Proxy27.getText(Unknown Source)\r\n\tat com.juaracoding.soalautomation.page.CheckoutPage.CheckOutPageValidation(CheckoutPage.java:68)\r\n\tat com.juaracoding.soalautomation.impl.CheckOutTesting.test007_validasi_checkout_page(CheckOutTesting.java:51)\r\n\tat ✽.Test007 Validasi CheckOut Page(file:///D:/Bootcamp%20SQA%20Juara%20Koding/SoalTestAutomation/src/main/resources/features/004CheckOutFeature.feature:3)\r\n","duration":13737612900,"status":"failed"},"line":3,"name":"Test007 Validasi CheckOut Page","match":{"location":"com.juaracoding.soalautomation.impl.CheckOutTesting.test007_validasi_checkout_page()"},"after":[{"result":{"error_message":"org.openqa.selenium.NoSuchWindowException: no such window: target window already closed\nfrom unknown error: web view not found\n  (Session info: chrome=130.0.6723.92)\nBuild info: version: '4.19.1', revision: 'abe0ee07dc'\nSystem info: os.name: 'Windows 10', os.arch: 'amd64', os.version: '10.0', java.version: '17.0.8'\nDriver info: org.openqa.selenium.chrome.ChromeDriver\nCommand: [6620f8f3aa088ee1244b99544fcb7077, screenshot {}]\nCapabilities {acceptInsecureCerts: false, browserName: chrome, browserVersion: 130.0.6723.92, chrome: {chromedriverVersion: 130.0.6723.91 (53ac07678369..., userDataDir: C:\\Users\\MSI\\AppData\\Local\\...}, fedcm:accounts: true, goog:chromeOptions: {debuggerAddress: localhost:64392}, networkConnectionEnabled: false, pageLoadStrategy: normal, platformName: windows, proxy: Proxy(), se:cdp: ws://localhost:64392/devtoo..., se:cdpVersion: 130.0.6723.92, setWindowRect: true, strictFileInteractability: false, timeouts: {implicit: 0, pageLoad: 300000, script: 30000}, unhandledPromptBehavior: dismiss and notify, webauthn:extension:credBlob: true, webauthn:extension:largeBlob: true, webauthn:extension:minPinLength: true, webauthn:extension:prf: true, webauthn:virtualAuthenticators: true}\nSession ID: 6620f8f3aa088ee1244b99544fcb7077\r\n\tat java.base/jdk.internal.reflect.NativeConstructorAccessorImpl.newInstance0(Native Method)\r\n\tat java.base/jdk.internal.reflect.NativeConstructorAccessorImpl.newInstance(NativeConstructorAccessorImpl.java:77)\r\n\tat java.base/jdk.internal.reflect.DelegatingConstructorAccessorImpl.newInstance(DelegatingConstructorAccessorImpl.java:45)\r\n\tat java.base/java.lang.reflect.Constructor.newInstanceWithCaller(Constructor.java:499)\r\n\tat java.base/java.lang.reflect.Constructor.newInstance(Constructor.java:480)\r\n\tat org.openqa.selenium.remote.ErrorCodec.decode(ErrorCodec.java:167)\r\n\tat org.openqa.selenium.remote.codec.w3c.W3CHttpResponseCodec.decode(W3CHttpResponseCodec.java:138)\r\n\tat org.openqa.selenium.remote.codec.w3c.W3CHttpResponseCodec.decode(W3CHttpResponseCodec.java:50)\r\n\tat org.openqa.selenium.remote.HttpCommandExecutor.execute(HttpCommandExecutor.java:190)\r\n\tat org.openqa.selenium.remote.service.DriverCommandExecutor.invokeExecute(DriverCommandExecutor.java:216)\r\n\tat org.openqa.selenium.remote.service.DriverCommandExecutor.execute(DriverCommandExecutor.java:174)\r\n\tat org.openqa.selenium.remote.RemoteWebDriver.execute(RemoteWebDriver.java:518)\r\n\tat org.openqa.selenium.remote.RemoteWebDriver.execute(RemoteWebDriver.java:591)\r\n\tat org.openqa.selenium.remote.RemoteWebDriver.execute(RemoteWebDriver.java:595)\r\n\tat org.openqa.selenium.remote.RemoteWebDriver.getScreenshotAs(RemoteWebDriver.java:321)\r\n\tat com.juaracoding.soalautomation.util.GlobalFunction.getScreenshot(GlobalFunction.java:21)\r\n\tat com.juaracoding.soalautomation.impl.LoginOutlineHooks.getResultStatus(LoginOutlineHooks.java:47)\r\n","duration":21737300,"status":"failed"},"match":{"location":"com.juaracoding.soalautomation.impl.LoginOutlineHooks.getResultStatus(io.cucumber.java.Scenario)"}}],"keyword":"When "},{"result":{"status":"skipped"},"line":4,"name":"Test007 Input TextField budi Yang Valid One","match":{"arguments":[{"val":"budi","offset":24}],"location":"com.juaracoding.soalautomation.impl.CheckOutTesting.test007_input_textfield_username_yang_valid_one(java.lang.String)"},"after":[{"result":{"duration":993700,"status":"skipped"},"match":{"location":"com.juaracoding.soalautomation.impl.LoginOutlineHooks.getResultStatus(io.cucumber.java.Scenario)"}}],"keyword":"And "},{"result":{"status":"skipped"},"line":5,"name":"Test007 Input TextField indonesia Yang Valid Two","match":{"arguments":[{"val":"indonesia","offset":24}],"location":"com.juaracoding.soalautomation.impl.CheckOutTesting.test007_input_textfield_password_yang_valid_two(java.lang.String)"},"after":[{"result":{"status":"skipped"},"match":{"location":"com.juaracoding.soalautomation.impl.LoginOutlineHooks.getResultStatus(io.cucumber.java.Scenario)"}}],"keyword":"And "},{"result":{"status":"skipped"},"line":6,"name":"Test007 Input TextField banyumas Yang Valid Three","match":{"arguments":[{"val":"banyumas","offset":24}],"location":"com.juaracoding.soalautomation.impl.CheckOutTesting.test007_input_textfield_password_yang_valid_three(java.lang.String)"},"after":[{"result":{"status":"skipped"},"match":{"location":"com.juaracoding.soalautomation.impl.LoginOutlineHooks.getResultStatus(io.cucumber.java.Scenario)"}}],"keyword":"And "},{"result":{"duration":1003100,"status":"skipped"},"line":7,"name":"Test007 Input TextField 55612345 Yang Valid Four","match":{"arguments":[{"val":"55612345","offset":24}],"location":"com.juaracoding.soalautomation.impl.CheckOutTesting.test007_input_textfield_password_yang_valid_four(java.lang.String)"},"after":[{"result":{"status":"skipped"},"match":{"location":"com.juaracoding.soalautomation.impl.LoginOutlineHooks.getResultStatus(io.cucumber.java.Scenario)"}}],"keyword":"And "},{"result":{"status":"skipped"},"line":8,"name":"Test007 Input TextField March Yang Valid Five","match":{"arguments":[{"val":"March","offset":24}],"location":"com.juaracoding.soalautomation.impl.CheckOutTesting.test007_input_textfield_password_yang_valid_five(java.lang.String)"},"after":[{"result":{"status":"skipped"},"match":{"location":"com.juaracoding.soalautomation.impl.LoginOutlineHooks.getResultStatus(io.cucumber.java.Scenario)"}}],"keyword":"And "},{"result":{"duration":899500,"status":"skipped"},"line":9,"name":"Test007 Input TextField 2024 Yang Valid Six","match":{"arguments":[{"val":"2024","offset":24}],"location":"com.juaracoding.soalautomation.impl.CheckOutTesting.test007_input_textfield_password_yang_valid_six(java.lang.String)"},"after":[{"result":{"duration":985000,"status":"skipped"},"match":{"location":"com.juaracoding.soalautomation.impl.LoginOutlineHooks.getResultStatus(io.cucumber.java.Scenario)"}}],"keyword":"And "},{"result":{"duration":1337000,"status":"skipped"},"line":10,"name":"Test007 Click Button purchase","match":{"location":"com.juaracoding.soalautomation.impl.CheckOutTesting.test007_click_button_purchase()"},"after":[{"result":{"status":"skipped"},"match":{"location":"com.juaracoding.soalautomation.impl.LoginOutlineHooks.getResultStatus(io.cucumber.java.Scenario)"}}],"keyword":"And "},{"result":{"status":"skipped"},"line":11,"name":"Test007 Validasi Check Out Form","match":{"location":"com.juaracoding.soalautomation.impl.CheckOutTesting.test007_validasi_check_out_form()"},"after":[{"result":{"status":"skipped"},"match":{"location":"com.juaracoding.soalautomation.impl.LoginOutlineHooks.getResultStatus(io.cucumber.java.Scenario)"}}],"keyword":"And "},{"result":{"status":"skipped"},"line":12,"name":"Test007 Click Button Ok","match":{"location":"com.juaracoding.soalautomation.impl.CheckOutTesting.test007_click_button_ok_()"},"after":[{"result":{"status":"skipped"},"match":{"location":"com.juaracoding.soalautomation.impl.LoginOutlineHooks.getResultStatus(io.cucumber.java.Scenario)"}}],"keyword":"And "},{"result":{"status":"skipped"},"line":13,"name":"Test007 Validasi website","match":{"location":"com.juaracoding.soalautomation.impl.CheckOutTesting.test007_validasi_website()"},"after":[{"result":{"status":"skipped"},"match":{"location":"com.juaracoding.soalautomation.impl.LoginOutlineHooks.getResultStatus(io.cucumber.java.Scenario)"}}],"keyword":"And "},{"result":{"status":"skipped"},"line":14,"name":"Test007 Click Button Log Out","match":{"location":"com.juaracoding.soalautomation.impl.CheckOutTesting.test007_click_button_log_out()"},"after":[{"result":{"status":"skipped"},"match":{"location":"com.juaracoding.soalautomation.impl.LoginOutlineHooks.getResultStatus(io.cucumber.java.Scenario)"}}],"keyword":"Then "}]}],"name":"Checkout Website","description":"","id":"checkout-website","keyword":"Feature","uri":"file:src/main/resources/features/004CheckOutFeature.feature","tags":[]}]